<?xml version="1.0" encoding="utf-8" standalone="yes" ?>

<!-- XtraSetup German Text -->
<!-- Translation by Marcus Carra <marcus@mcs-webdesign.com> -->

<Resources Language="de">

	<!-- Misc -->
	<String ID="InstallTitle">{0} Installation</String>
	<String ID="InstallLabel">{0} Installation</String>

	<!-- Main Page -->
	<String ID="WelcomePageTitle">Willkommen</String>
	<String ID="WelcomeTitle">Willkommen zum {0} Installationsprogramm</String>
	<String ID="WelcomeInstructions">Mit dem Installieren dieses Programmes stimmen Sie zu,&#10;dass Sie die Lizensbestimmung gelesen und akzeptiert haben.</String>
<!--
	<String ID="WelcomeInstructions">Um die Installation zu beginnen, klicke Installieren.&#10;Um die Installation zu personalisieren, klicke den Optionen Tab.</String>
-->
	<String ID="WelcomeInfoURL">Lernen Sie mehr über {0}</String>
	<String ID="OpenBetaWarningURL">WARNUNG: Um diese Version zu nutzen, benötigen Sie einen Produktschlüssel</String>
	<String ID="ClosedBetaWarning">WARNUNG: Dies ist ein interner Beta Test. Verbreiten Sie diese Version nicht!</String>

	<String ID="LicensePageTitle">Lizens</String>

	<String ID="OptionsPageTitle">Optionen</String>
	<String ID="InstallFolders">Ordner</String>
	<String ID="InstallFolderLabel">{0} wird in folgenden Ordner installiert:</String>
	<String ID="SpaceRequired">Benötigter Platz: {0,.0} MB</String>
	<String ID="ProgramGroupLabel">Programmicons werden folgender Gruppe hinzugefügt:</String>
	<String ID="ShortcutsGroup">Zusätzliche Tastenkürzel</String>
	<String ID="CreateDesktopShortcut">Erstelle ein &amp;Desktopicon</String>
	<String ID="CreateQuickLaunchShortcut">Erstelle ein &amp;Quick Launch Icon</String>

	<String ID="BrowseInstallFolderHelp">Wählen Sie den Instalationsordner:</String>

	<!-- File Transfer Page -->
	<String ID="InstallInProgress">Installation wird durchgeführt...</String>
	<String ID="ProgressionText">Schreibe Dateien: {0,.0}% geschafft</String>
	<String ID="TimeRemaining">Verbleibende Zeit:</String>
	<String ID="CancelConfirmation">Sind Sie sicher, dass sie die {0} Installation abbrechen wollen?</String>

	<!-- Canceled Page -->
	<String ID="InstallCanceled">Installation abgebrochen</String>
	<String ID="CanceledMessage">Der Installationsprozess wurde erfolgreich abgebrochen</String>

	<!-- Failure Page -->
	<String ID="InstallFailed">Installation fehlgeschlagen</String>
	<String ID="FailureMessage">Bitte vergewissern Sie sich, dass Sie genügend Zugriffsrechte und freien Festplattenplatz&#10;haben, bevor Sie den Softwarehersteller kontaktieren.</String>
	<String ID="TechnicalSupport">Technicher Support</String>

	<!-- Success Page -->
	<String ID="InstallSucceeded">Installation erfolgreich</String>
	<String ID="SuccessMessage">{0} wurde erfolgreich installiert.</String>
	<String ID="OfficialWebSiteInfo">Detailierte Dokumentationen und die neuesten Updates finden Sie auf der offiziellen Webseite.</String>

	<!-- Buttons -->
	<String ID="InstallButton">&amp;Installieren</String>
	<String ID="RunButton">&amp;Starten {0}</String>

</Resources>
